importopoi/__init__.py
importopoi/cli.py
importopoi/graph.py
importopoi/import_inventory.py
importopoi/imports.py
importopoi/log_utils.py
importopoi/pprint_utils.py
importopoi/py.typed
importopoi-0.0.2.dist-info/LICENSE
importopoi-0.0.2.dist-info/METADATA
importopoi-0.0.2.dist-info/WHEEL
importopoi-0.0.2.dist-info/entry_points.txt
importopoi-0.0.2.dist-info/top_level.txt
importopoi-0.0.2.dist-info/RECORD
